passgenius/__init__.py
passgenius/__main__.py
passgenius/checker.py
passgenius/generator.py
passgenius-0.1.0.dist-info/licenses/LICENSE
passgenius-0.1.0.dist-info/METADATA
passgenius-0.1.0.dist-info/WHEEL
passgenius-0.1.0.dist-info/entry_points.txt
passgenius-0.1.0.dist-info/top_level.txt
passgenius-0.1.0.dist-info/RECORD
