Metadata-Version: 2.4
Name: passgenius
Version: 0.1.0
Summary: A smart password generator and strength checker
Author-email: Nasarah Peter Dashe <godwinfirstfruit4b@gmail.com>
License: MIT
Keywords: password,generator,security,checker
Requires-Python: >=3.8
License-File: LICENSE
Dynamic: license-file
